MANIFEST.in
Makefile
README.md
README.rst
requirements-dev.txt
requirements.txt
setup.py
tox.ini
demo/biquad_filter_design.py
demo/comb_filter_design.py
demo/custom_filter_design.py
demo/fourier_analysis.py
demo/parametric_equalizer_design.py
demo/single_pole_filter_design.py
demo/state_variable_filter_design.py
demo/windowed_sinc_filter_design.py
docs/Makefile
docs/conf.py
docs/index.rst
docs/make.bat
docs/modules.rst
docs/yodel.analysis.rst
docs/yodel.complex.rst
docs/yodel.conversion.rst
docs/yodel.delay.rst
docs/yodel.filter.rst
docs/yodel.rst
test/test_analysis_fft.py
test/test_analysis_window.py
test/test_complex.py
test/test_conversion.py
test/test_delay_delayline.py
test/test_filter_biquad.py
test/test_filter_comb.py
test/test_filter_convolution.py
test/test_filter_custom.py
test/test_filter_parametric_eq.py
test/test_filter_single_pole.py
test/test_filter_state_variable.py
test/test_filter_windowedsinc.py
yodel/__init__.py
yodel/analysis.py
yodel/complex.py
yodel/conversion.py
yodel/delay.py
yodel/filter.py
yodel.egg-info/PKG-INFO
yodel.egg-info/SOURCES.txt
yodel.egg-info/dependency_links.txt
yodel.egg-info/top_level.txt