Metadata-Version: 1.0
Name: yodel
Version: 0.3.0
Summary: The Swiss Army knife for your sound
Home-page: https://github.com/rclement/yodel
Author: Romain Clement
Author-email: contact@romainclement.com
License: MIT
Platform: any
